{"name": "Deep Learning", "email": "aarshibhatt112@gmail.com", "mobile_number": null, "skills": ["Python", "Sci", "Biology", "Engineering", "Ai", "Facebook", "Html", "Content", "Computer science", "Machine learning", "Usability", "English", "Website", "Javascript", "Css", "Analyze"], "college_name": null, "degree": null, "designation": null, "experience": ["Google AI | Explore ML Facilitator:", "Organized a series of workshop for students to get started with machine learning.", "Impacted 100+ university or college students.", "Kaggle Days (Delhi - NCR):", "Volunteer in content development for the blogs, interview of speakers, Kaggle", "master, grandmaster and organizing meetups for getting started with Kaggle."], "company_names": null, "no_of_pages": 1, "total_experience": 0.0}